hash_ocr/__init__.py
hash_ocr/label.py
hash_ocr/py.typed
hash_ocr/models/beaufont.json
hash_ocr/models/beaufont.png
hash_ocr/models/segoe_ui_9.json
hash_ocr/models/segoe_ui_9.png
hash_ocr/models/speigel_8.json
hash_ocr/models/speigel_8.png
hash_ocr-2.2.5.dist-info/LICENSE
hash_ocr-2.2.5.dist-info/METADATA
hash_ocr-2.2.5.dist-info/WHEEL
hash_ocr-2.2.5.dist-info/top_level.txt
hash_ocr-2.2.5.dist-info/RECORD
