Metadata-Version: 2.1
Name: hash-ocr
Version: 2.2.5
Summary: Fast OCR to read computer rendered texts
Author-email: Pradish Bijukchhe <pradish@sandbox.com.np>
License: Copyright (c) 2018 The Python Packaging Authority
Project-URL: Homepage, https://github.com/sandbox-pokhara/hash-ocr
Project-URL: Issues, https://github.com/sandbox-pokhara/hash-ocr/issues
Classifier: Programming Language :: Python :: 3
Requires-Python: >=3
License-File: LICENSE
Requires-Dist: opencv-python
Requires-Dist: opencv-contrib-python
